embypy/__init__.py
embypy/__main__.py
embypy/emby.py
embypy/objects/__init__.py
embypy/objects/folders.py
embypy/objects/misc.py
embypy/objects/object.py
embypy/objects/videos.py
embypy/utils/__init__.py
embypy/utils/connector.py
EmbyPy-0.4.5.1.dist-info/LICENSE.txt
EmbyPy-0.4.5.1.dist-info/METADATA
EmbyPy-0.4.5.1.dist-info/WHEEL
EmbyPy-0.4.5.1.dist-info/top_level.txt
EmbyPy-0.4.5.1.dist-info/RECORD
